RoboShodan.py
RoboShodan-1.0.dist-info/DESCRIPTION.rst
RoboShodan-1.0.dist-info/METADATA
RoboShodan-1.0.dist-info/RECORD
RoboShodan-1.0.dist-info/WHEEL
RoboShodan-1.0.dist-info/metadata.json
RoboShodan-1.0.dist-info/top_level.txt
