Metadata-Version: 2.0
Name: RoboShodan
Version: 1.0
Summary: Robot Framework Library for Shodan
Home-page: https://github.com/we45/RoboShodan
Author: we45
Author-email: info@we45.com
License: MIT
Platform: UNKNOWN
Requires-Dist: shodan
Requires-Dist: robotframework (==3.0.4)
